{
    "Type": "Parameters",
    "OutputDirectory": "/home/dtcc/core/data/output/MinimalCase",
    "DomainHeight": 50.0,
    "ElevationModelResolution": 1.0,
    "MeshResolution": 5.0,
    "X0": 0,
    "Y0": 0,
    "AutoDomain": true,
    "DomainMargin": 3.0,
    "MinBuildingDistance": 1.0,
    "MinVertexDistance": 1.0,
    "GroundMargin": 1.0,
    "OutlierMargin": 12.0,
    "GroundPercentile": 0.1,
    "RoofPercentile": 0.9,
    "GroundSmoothing": 2,
    "GenerateSurfaceMeshes": true,
    "GenerateVolumeMeshes": true,
    "WriteJSON": true,
    "WriteVTK": true,
    "Debug": true,
    "BuildingRemoveOutlier": false,
    "OutlierNeighbors": 5,
    "OutlierSTD": 2.0
}