{
    "Type": "Parameters",
    "DataDirectory": "/home/dtcc/dtcc-builder/data/Helsingborg2021",
    "DomainHeight": 100.0,
    "ElevationModelResolution": 1.0,
    "MeshResolution": 20.0,
    "AutoDomain": true,
    "MinBuildingDistance": 1.0,
    "MinVertexDistance": 1.0,
    "GroundMargin": 1.0,
    "GroundPercentile": 0.1,
    "RoofPercentile": 0.9,
    "OutlierMargin": 2.0,
    "GroundSmoothing": 2,
    "NumRandomBuildings": 1000,
    "GenerateSurfaceMeshes": true,
    "GenerateVolumeMeshes": true,
    "WriteJSON": true,
    "WriteVTK": true,
    "Debug": false
}
